reflex_local_auth/__init__.py
reflex_local_auth/auth_session.py
reflex_local_auth/local_auth.py
reflex_local_auth/login.py
reflex_local_auth/registration.py
reflex_local_auth/routes.py
reflex_local_auth/user.py
reflex_local_auth/pages/__init__.py
reflex_local_auth/pages/components.py
reflex_local_auth/pages/login.py
reflex_local_auth/pages/registration.py
reflex_local_auth-0.4.0.dist-info/METADATA
reflex_local_auth-0.4.0.dist-info/WHEEL
reflex_local_auth-0.4.0.dist-info/top_level.txt
reflex_local_auth-0.4.0.dist-info/RECORD
