Metadata-Version: 2.4
Name: reflex-local-auth
Version: 0.4.0
Summary: Local DB user authentication for Reflex apps
Author-email: Masen Furer <m_github@0x26.net>
License: Apache-2.0
Project-URL: Homepage, https://github.com/masenf/reflex-local-auth
Keywords: reflex,reflex-custom-components
Classifier: Development Status :: 4 - Beta
Requires-Python: >=3.10
Requires-Dist: reflex>=0.8.1
Requires-Dist: bcrypt
Provides-Extra: dev
Requires-Dist: build; extra == "dev"
Requires-Dist: twine; extra == "dev"
